{"cameraMode":{"drawMode":0,"name":"Shaded","section":"Shading Mode"},"sceneLighting":false,"audioPlay":false,"sceneViewState":{"showFog":true,"showMaterialUpdate":false,"showSkybox":false,"showFlares":true,"showImageEffects":true,"showParticleSystems":true},"in2DMode":false,"pivot":{"x":-0.015163690783083439,"y":1.0019347667694092,"z":0.08616198599338532},"rotation":{"x":-0.25096800923347475,"y":-0.16827090084552766,"z":0.044349391013383868,"w":-0.9522253274917603},"size":0.7171286940574646,"orthographic":false}